banner/__init__.py
banner/connection.py
banner/pandas_decorator.py
banner/pandas_wrap.py
banner/queries.py
banner/utils/__init__.py
banner/utils/const.py
banner/utils/misc.py
banner/utils/neware.py
banner/utils/pandas.py
banner/utils/web2py.py
banner_storedot-2.3.9.dist-info/LICENSE
banner_storedot-2.3.9.dist-info/METADATA
banner_storedot-2.3.9.dist-info/WHEEL
banner_storedot-2.3.9.dist-info/top_level.txt
banner_storedot-2.3.9.dist-info/RECORD
