Metadata-Version: 2.1
Name: banner-storedot
Version: 2.3.9
Summary: light dal package
Home-page: https://https://github.com/storedot/banner
Author: GB
Author-email: techsupport@store-dot.com
Project-URL: Bug Tracker, https://https://github.com/storedot/banner/issues
Classifier: Programming Language :: Python :: 3
Classifier: License :: OSI Approved :: MIT License
Classifier: Operating System :: OS Independent
Requires-Python: >=3.8
License-File: LICENSE
Requires-Dist: wheel
Requires-Dist: mysqlclient
Requires-Dist: redis>=4.3.3
Requires-Dist: pandas>=1.3.2
Requires-Dist: joblib>=1.1.0
Requires-Dist: psycopg2>=2.9.3
